Workbook

Sheet B1装修管控总表（优化版）
A1: 商铺号 | C1: 商铺名称 | D1: 面积㎡ | E1: 招商拉群对接 | F1: 运营对接人 | G1: 围挡搭建 | H1: 合作意向确认 | I1: 是否给到红线 | J1: 合同约定接铺时间 | K1: 预计进场时间 | L1: 是否进场 | M1: 实际接铺时间 | N1: 平面图预计出图时间 | O1: 效果图预计出图时间 | P1: 施工图预计出图时间 | Q1: 平面图实际出图时间 | R1: 效果图实际出图实际 | S1: 施工图实际出图时间 | T1: 施工保险 | U1: 门头施工交底 | V1: 营业执照是否取得 | W1: 食品经营许可证取得 | X1: 消防改造是否完成 | Y1: 空调改造是否完成 | Z1: 闭水验收 | AA1: 隐蔽验收 | AB1: 合同约定开业日期 | AC1: 预计开业时间 | AD1: 提前开业天数 | AE1: 提前开业租金 | AF1: 目前施工状态
A2: 改造后-超市区域 | B2: A栋-B1-40 | C2: 树夏 | D2: 100.12
B3: A栋-B1-41 | C3: OPPO | D3: 110.91 | E3: 是 | F3: 宫笑 | I3: 是 | K3: 7.5 | L3: 否 | N3: 6.5 | O3: 6.12 | P3: 6.18
B4: A栋-B1-42 | C4: VIVO | D4: 66.49 | E4: 是 | F4: 宫笑 | I4: 是 | K4: 7.5 | L4: 否 | N4: 6.5 | O4: 6.12 | P4: 6.18
B5: A栋-B1-43 | C5: 同方药业 | D5: 71.7 | E5: 是 | F5: 冷娜 | I5: 是 | K5: 7.5 | L5: 否 | N5: 6.2 | O5: 6.11 | P5: 6.15 | R5: 是
B6: A栋-B1-45 | C6: 诺特兰德 | D6: 64.83
B7: A栋-B1-46 | C7: 科大讯飞 | D7: 64.83 | H7: 5.28
B8: A栋-B1-47 | C8: 洗脸猫 | D8: 67.58 | E8: 是 | F8: 冷娜 | I8: 是 | K8: 7.5 | L8: 否 | N8: 已出图调整修改中 | O8: 6.11 | P8: 6.15 | Q8: 是
B9: A栋-B1-48 | C9: 卡游 | D9: 75.07
B10: A栋-B1-49 | C10: 宠有家 | D10: 135.41 | E10: 是 | F10: 薛洁 | I10: 是 | K10: 7.5 | L10: 否
B11: A栋-B1-50 | C11: 宠有家 | D11: 48.75 | E11: 是 | F11: 薛洁 | I11: 是 | K11: 7.5 | L11: 否
B12: A-B1-Z01 | C12: 超市 | D12: 3836.72 | E12: 是 | F12: 孟祥臻 | I12: 是 | K12: 7.5 | L12: 否 | N12: 6.2（第一版已出） | O12: 6.11 | P12: 6.18
A13: 改造后-中岛 | B13: A栋-B1-53 | C13: SKG-营运外摆 | D13: 23.44
B14: A栋-B1-54 | C14: 添可-营运外摆 | D14: 17.85
B15: A栋-B1-55 | C15: DYSON-营运外摆 | D15: 17.85
B16: A栋-B1-56 | C16: 李山山茶室 | D16: 16.52
B17: A栋-B1-57 | C17: 李山山外摆 | D17: 17.72
B18: A栋-B1-58 | C18: 琦王花生 | D18: 11.33 | E18: 是 | F18: 许如邯 | L18: 否
B19: A栋-B1-59 | C19: 薛记 | D19: 11.33 | E19: 是 | F19: 孟祥臻 | L19: 否
B20: A栋-B1-60 | C20: 目光眼镜 | D20: 22.28 | E20: 是 | F20: 冷娜 | K20: 7.10 | L20: 否 | N20: 已出图审核中 | O20: 已出图审核中 | P20: 6.15 | Q20: 5.29 | R20: 5.29
B21: A栋-B1-61 | C21: 膜壳先锋 | D21: 11.7 | E21: 否 | F21: 冷娜
B22: A栋-B1-62 | C22: 瑞幸外摆 | D22: 10.73 | E22: 6.15 | F22: 张潇 | L22: 否
B23: A栋-B1-63 | C23: 罗曼林 | D23: 13.65
B24: A栋-B1-64 | C24: 德菲梵 | D24: 13.65
B25: A栋-B1-65 | C25: 名之屋 | D25: 16.74
B26: A栋-B1-66 | C26: 柑啵啵 | D26: 15.3
B27: A栋-B1-67 | C27: 有堂古 | D27: 16.24
B28: A栋-B1-68 | C28: 鲜目录寿司 | D28: 14.8
B29: A栋-B1-69 | C29: 德菲凡 | D29: 12.4
B30: A栋-B1-70 | C30: 果小铺 | D30: 15.2
B31: A栋-B1-71 | C31: 周黑鸭 | D31: 12.9 | E31: 是 | F31: 孟祥臻 | H31: 5.31 | K31: 7.2 | L31: 否 | N31: 6.15 | O31: 6.21 | P31: 7.1
B32: A栋-B1-72 | C32: 琴岛留香 | D32: 15.38 | E32: 是 | F32: 孟祥臻 | H32: 5.31 | K32: 7.2 | L32: 否 | N32: 6.15 | O32: 6.21 | P32: 7.1
B33: A栋-B1-73 | C33: 巧克叔叔 | D33: 17.51
B34: A栋-B1-74 | C34: 糖小妙 | D34: 17.83
B35: A栋-B1-75 | C35: fufuland | D35: 17.83
B36: A栋-B1-76 | C36: 茉酸奶 | D36: 37.22
A37: 改造后-边铺 | B37: A栋-B1-01 | C37: 比木.卡西西 | D37: 142.42
B38: A栋-B1-02 | C38: 嗨嗨儿 | D38: 119.87 | E38: / | F38: /
B39: A栋-B1-03 | C39: 犟骨头超级排骨饭 | D39: 62.56 | E39: 是 | F39: 孟祥臻 | K39: 6.16 | L39: 否 | N39: 6.5 | O39: 6.6 | P39: 6.14
B40: A栋-B1-05 | C40: 品秦川 | D40: 148.01 | E40: 是 | F40: 孟祥臻 | K40: 6.16 | L40: 否 | N40: 6.5 | O40: 6.1
B41: A栋-B1-06 | C41: 太犇牛 | D41: 65.3
B42: A栋-B1-07 | C42: 丹香 | D42: 140.42 | E42: 是 | F42: 孟祥臻 | G42: 是 | I42: 是 | J42: 46189 | K42: 6.16 | L42: 否 | N42: 5.26 | O42: 6.8 | P42: 6.14
B43: A栋-B1-08 | C43: 宫合记 | D43: 99.41 | E43: 是 | F43: 孟祥臻 | G43: 是 | I43: 是 | J43: 46190 | K43: 6.17 | L43: 否 | N43: 5.28 | O43: 6.1 | P43: 6.15 | Q43: 是
B44: A栋-B1-09 | C44: 李若桃 | D44: 70.39
B45: A栋-B1-10，A栋-B1-11a | C45: 花小福 | D45: 154.85 | E45: / | F45: /
B46: A栋-B1-11b | C46: 柠季 | D46: 95.24
B47: A栋-B1-12a，A栋-B1-12b | C47: 瑞幸 | D47: 66.45 | E47: 6.15 | F47: 张潇
B48: A栋-B1-13 | C48: 联想 | D48: 84.65 | E48: 是 | F48: 宫笑 | N48: 6.5 | O48: 6.12 | P48: 6.18
B49: A栋-B1-15 | C49: 转转 | D49: 84.47 | E49: / | F49: /
B50: A栋-B1-16 | C50: 任天堂 | D50: 62.25
B51: A栋-B1-17 | C51: 阿香米线 | D51: 95.3 | E51: 是 | F51: 孟祥臻 | K51: 7.25 | L51: 否 | N51: 6.5 | O51: 6.5 | P51: 6.15
B52: A栋-B1-18a | C52: 满巍明 | D52: 14.51 | E52: 是 | F52: 孟祥臻 | K52: 7.2 | L52: 否 | N52: 6.12 | O52: 6.18 | P52: 6.25
B53: A栋-B1-18b | C53: 玖铭 | D53: 10.82 | E53: 是 | F53: 孟祥臻
B54: A栋-B1-19b | C54: 鹏程脂渣 | D54: 51.57 | E54: 6.3 | F54: 张潇
B55: A栋-B1-20 | C55: 米村 | D55: 130.74 | E55: 6.5 | F55: 许如邯
B56: A栋-B1-21 | C56: 天府国 | D56: 107.67 | E56: 是 | F56: 张潇 | G56: 沟通出图中 | I56: 是 | L56: 否
B57: A栋-B1-22 | C57: 喻记南派 | D57: 86.48 | E57: 是 | F57: 孟祥臻
B58: A栋-B1-23.25 | C58: 尹三顺 | D58: 287.56 | E58: 是 | F58: 许如邯 | G58: 已出图待付款 | I58: 是 | J58: 46189 | K58: 6.12 | L58: 否 | N58: 已出，门头区域待定，结合效果图看 | O58: 已出，审核中 | P58: 6.11 | Q58: 是
B59: A栋-B1-26 | C59: 福彩 | D59: 27.87 | E59: 是 | F59: 冷娜 | G59: 已出图待付款 | I59: 是 | J59: 46189 | K59: 2026/6/16 | L59: FOU | N59: 6.4 | O59: 6.9 | P59: 6.15
B60: A栋-B1-C01 | C60: 欧黎雅动漫 | D60: 4 | E60: / | F60: / | G60: / | H60: / | I60: / | J60: / | K60: / | L60: / | M60: / | N60: / | O60: / | P60: / | Q60: / | R60: / | S60: / | T60: / | U60: / | V60: / | W60: / | X60: / | Y60: / | Z60: / | AA60: /
B61: A栋-B1-C05 | C61: 小铁 | D61: 2.84 | E61: / | F61: / | G61: / | H61: / | I61: / | J61: / | K61: / | L61: / | M61: / | N61: / | O61: / | P61: / | Q61: / | R61: / | S61: / | T61: / | U61: / | V61: / | W61: / | X61: / | Y61: / | Z61: / | AA61: /
B62: A栋-B1-C05 | C62: 乐摩吧 | D62: 4 | E62: / | F62: / | G62: / | H62: / | I62: / | J62: / | K62: / | L62: / | M62: / | N62: / | O62: / | P62: / | Q62: / | R62: / | S62: / | T62: / | U62: / | V62: / | W62: / | X62: / | Y62: / | Z62: / | AA62: / | AB62: 46220
B64: 汇总 | C64: 总品牌数 | D64: 60 | F64: 总面积㎡ | G64: ==SUM(D2:D64) -> 7319.46
A73: B1装修管控看板 (动态实时更新)
A75: 核心进度
A76: 指标名称 | B76: 当前完成数 | C76: 总数 | D76: 完成百分比
A77: 招商拉群对接率 | B77: ==COUNTIF('B1装修管控总表（优化版）'!E:E,"是") -> 24 | C77: ==COUNTA(C2:C62) -> 61 | D77: ==B77/C77 -> 0.39344262
A78: 围挡搭建率 | B78: ==COUNTIF('B1装修管控总表（优化版）'!G:G,"是") -> 2 | C78: ==COUNTA(C2:C63) -> 61 | D78: ==B78/C78 -> 0.032786885
A79: 平面图出图率 | B79: ==COUNTIF('B1装修管控总表（优化版）'!Q:Q,"是") -> 3 | C79: ==COUNTA(C2:C63) -> 61 | D79: ==B79/C79 -> 0.049180328
A80: 效果图出图率 | B80: ==COUNTIF('B1装修管控总表（优化版）'!R:R,"是") -> 1 | C80: ==COUNTA(C2:C63) -> 61 | D80: ==B80/C80 -> 0.016393443
A81: 施工图有出图率 | B81: ==COUNTIF('B1装修管控总表（优化版）'!S:S,"是") -> 0 | C81: ==COUNTA(C2:C62) -> 61 | D81: ==B81/C81 -> 0
A82: 实际进场率 | B82: ==COUNTIF('B1装修管控总表（优化版）'!L90:L167,"是") -> 0 | C82: ==COUNTA(C2:C62) -> 61 | D82: ==B82/C82 -> 0
A86: 三大区域进度透视 | F86: 三大区域进度透视
A87: 区域名称 | B87: 总店铺数 | C87: 拉群对接数 | D87: 红线确认数量 | E87: 围挡搭建数 | F87: 平面出图数 | G87: 效果出图数 | H87: 施工图出图数
A88: 超市区域 | B88: 11 | C88: ==COUNTIF('B1装修管控总表（优化版）'!E2:E12,"是") -> 7 | D88: ==COUNTIF('B1装修管控总表（优化版）'!I2:I12,"是") -> 7 | E88: ==COUNTIF('B1装修管控总表（优化版）'!G2:G12,"是") -> 0 | F88: ==COUNTIF('B1装修管控总表（优化版）'!Q2:Q12,"是") -> 1 | G88: ==COUNTIF('B1装修管控总表（优化版）'!R2:R12,"是") -> 1 | H88: ==COUNTIF('B1装修管控总表（优化版）'!S2:S12,"是") -> 0
A89: 中岛区域 | B89: 23 | C89: ==COUNTIF('B1装修管控总表（优化版）'!E13:E36,"是") -> 5 | D89: ==COUNTIF('B1装修管控总表（优化版）'!I13:I36,"是") -> 0 | E89: ==COUNTIF('B1装修管控总表（优化版）'!G13:G36,"是") -> 0 | F89: ==COUNTIF('B1装修管控总表（优化版）'!Q13:Q36,"是") -> 0 | G89: ==COUNTIF('B1装修管控总表（优化版）'!R13:R36,"是") -> 0 | H89: ==COUNTIF('B1装修管控总表（优化版）'!S13:S36,"是") -> 0
A90: 边铺区域 | B90: 25 | C90: ==COUNTIF('B1装修管控总表（优化版）'!E37:E62,"是") -> 12 | D90: ==COUNTIF('B1装修管控总表（优化版）'!I37:I62,"是") -> 5 | E90: ==COUNTIF('B1装修管控总表（优化版）'!G37:G62,"是") -> 2 | F90: ==COUNTIF('B1装修管控总表（优化版）'!Q37:Q62,"是") -> 2 | G90: ==COUNTIF('B1装修管控总表（优化版）'!R37:R62,"是") -> 0 | H90: ==COUNTIF('B1装修管控总表（优化版）'!S37:S62,"是") -> 0

Sheet 改造后B1招商预签品牌
A1: 改造后—超市区域
A2: 品牌 | B2: 资源号 | C2: 面积 | D2: 保底租金单价 | E2: 物管单价 | F2: 推广费单价 | K2: 全含 | L2: 月总租费，不含抽成 | M2: 月总租费，含抽成 | P2: 月总租费，含抽成 | Q2: 年总租费（含税，元）
C3: （平方米） | D3: （含税，元/平方米/月） | E3: （含税，元/平方米/月） | F3: （含税，元/平方米/月） | G3: 扣点 | H3: 取高临界值 | I3: 保守预估 | J3: 保守 | N3: 激进预估 | O3: 激进抽成 | R3: 保底租金 | S3: 物业 | T3: 推广
A4: oppo | B4: A栋-B1-40 | C4: 98.14 | D4: 130 | E4: 50 | F4: 10.6 | G4: 0.05 | H4: ==D4*C4/G4/1.09 -> 234095.41 | I4: 120000 | J4: ==(I4-H4)*G4*1.09 -> -6218.2 | K4: ==D4+E4+F4 -> 190.6 | L4: ==(D4+E4+F4)*C4 -> 18705.484 | M4: ==K4*C4+MAX(J4,0) -> 18705.484 | N4: 150000 | O4: ==(N4-H4)*G4*1.09 -> -4583.2 | P4: ==K4*C4+MAX(O4,0) -> 18705.484 | Q4: ==M4*12 -> 224465.81 | R4: ==C4*D4 -> 12758.2 | S4: ==E4*C4 -> 4907 | T4: ==F4*C4 -> 1040.284
A5: VIVO | B5: A栋-B1-41 | C5: 115.82 | D5: 120 | E5: 50 | F5: 10.6 | G5: 0.05 | H5: ==D5*C5/G5/1.09 -> 255016.51 | I5: 120000 | J5: ==(I5-H5)*G5*1.09 -> -7358.4 | K5: ==D5+E5+F5 -> 180.6 | L5: ==(D5+E5+F5)*C5 -> 20917.092 | M5: ==K5*C5+MAX(J5,0) -> 20917.092 | N5: 150000 | O5: ==(N5-H5)*G5*1.09 -> -5723.4 | P5: ==K5*C5+MAX(O5,0) -> 20917.092 | Q5: ==M5*12 -> 251005.1 | R5: ==C5*D5 -> 13898.4 | S5: ==E5*C5 -> 5791 | T5: ==F5*C5 -> 1227.692
A6: JINS | B6: A栋-B1-42 | C6: 69.45 | D6: 160 | E6: 50 | F6: 10.6 | G6: 0.11 | H6: ==D6*C6/G6/1.09 -> 92677.231 | I6: 75000 | J6: ==(I6-H6)*G6*1.09 -> -2119.5 | K6: ==D6+E6+F6 -> 220.6 | L6: ==(D6+E6+F6)*C6 -> 15320.67 | M6: ==K6*C6+MAX(J6,0) -> 15320.67 | N6: 100000 | O6: ==(N6-H6)*G6*1.09 -> 878 | P6: ==K6*C6+MAX(O6,0) -> 16198.67 | Q6: ==M6*12 -> 183848.04 | R6: ==C6*D6 -> 11112 | S6: ==E6*C6 -> 3472.5 | T6: ==F6*C6 -> 736.17
A7: 伽百利 | B7: A栋-B1-43 | C7: 74.61 | D7: 145 | E7: 50 | F7: 10.6 | G7: 0.11 | H7: ==D7*C7/G7/1.09 -> 90228.941 | I7: 75000 | J7: ==(I7-H7)*G7*1.09 -> -1825.95 | K7: ==D7+E7+F7 -> 205.6 | L7: ==(D7+E7+F7)*C7 -> 15339.816 | M7: ==K7*C7+MAX(J7,0) -> 15339.816 | N7: 100000 | O7: ==(N7-H7)*G7*1.09 -> 1171.55 | P7: ==K7*C7+MAX(O7,0) -> 16511.366 | Q7: ==M7*12 -> 184077.79 | R7: ==C7*D7 -> 10818.45 | S7: ==E7*C7 -> 3730.5 | T7: ==F7*C7 -> 790.866
A8: 科大讯飞 | B8: A栋-B1-45 | C8: 68.63 | D8: 155 | E8: 50 | F8: 10.6 | G8: 0.11 | H8: ==D8*C8/G8/1.09 -> 88721.018 | I8: 80000 | J8: ==(I8-H8)*G8*1.09 -> -1045.65 | K8: ==D8+E8+F8 -> 215.6 | L8: ==(D8+E8+F8)*C8 -> 14796.628 | M8: ==K8*C8+MAX(J8,0) -> 14796.628 | N8: 80000 | O8: ==(N8-H8)*G8*1.09 -> -1045.65 | P8: ==K8*C8+MAX(O8,0) -> 14796.628 | Q8: ==M8*12 -> 177559.54 | R8: ==C8*D8 -> 10637.65 | S8: ==E8*C8 -> 3431.5 | T8: ==F8*C8 -> 727.478
A9: 联想 | B9: A栋-B1-46 | C9: 66.83 | D9: 155 | E9: 50 | F9: 10.6 | G9: 0.05 | H9: ==D9*C9/G9/1.09 -> 190066.97 | I9: 120000 | J9: ==(I9-H9)*G9*1.09 -> -3818.65 | K9: ==D9+E9+F9 -> 215.6 | L9: ==(D9+E9+F9)*C9 -> 14408.548 | M9: ==K9*C9+MAX(J9,0) -> 14408.548 | N9: 150000 | O9: ==(N9-H9)*G9*1.09 -> -2183.65 | P9: ==K9*C9+MAX(O9,0) -> 14408.548 | Q9: ==M9*12 -> 172902.58 | R9: ==C9*D9 -> 10358.65 | S9: ==E9*C9 -> 3341.5 | T9: ==F9*C9 -> 708.398
A10: HIIDOLL | B10: A栋-B1-47 | C10: 72.95 | D10: 155 | E10: 50 | F10: 10.6 | G10: 0.05 | H10: ==D10*C10/G10/1.09 -> 207472.48 | I10: 120000 | J10: ==(I10-H10)*G10*1.09 -> -4767.25 | K10: ==D10+E10+F10 -> 215.6 | L10: ==(D10+E10+F10)*C10 -> 15728.02 | M10: ==K10*C10+MAX(J10,0) -> 15728.02 | N10: 140000 | O10: ==(N10-H10)*G10*1.09 -> -3677.25 | P10: ==K10*C10+MAX(O10,0) -> 15728.02 | Q10: ==M10*12 -> 188736.24 | R10: ==C10*D10 -> 11307.25 | S10: ==E10*C10 -> 3647.5 | T10: ==F10*C10 -> 773.27
A11: UMUYCASE | B11: A栋-B1-48 | C11: 77.36 | D11: 120 | E11: 50 | F11: 10.6 | G11: 0.11 | H11: ==D11*C11/G11/1.09 -> 77424.52 | I11: 80000 | J11: ==(I11-H11)*G11*1.09 -> 308.8 | K11: ==D11+E11+F11 -> 180.6 | L11: ==(D11+E11+F11)*C11 -> 13971.216 | M11: ==K11*C11+MAX(J11,0) -> 14280.016 | N11: 80000 | O11: ==(N11-H11)*G11*1.09 -> 308.8 | P11: ==K11*C11+MAX(O11,0) -> 14280.016 | Q11: ==M11*12 -> 171360.19 | R11: ==C11*D11 -> 9283.2 | S11: ==E11*C11 -> 3868 | T11: ==F11*C11 -> 820.016
A12: 九木杂物社 | B12: A栋-B1-49 | C12: 131.8 | D12: 105 | E12: 50 | F12: 10.6 | G12: 0.1 | H12: ==D12*C12/G12/1.09 -> 126963.3 | I12: 160000 | J12: ==(I12-H12)*G12*1.09 -> 3601 | K12: ==D12+E12+F12 -> 165.6 | L12: ==(D12+E12+F12)*C12 -> 21826.08 | M12: ==K12*C12+MAX(J12,0) -> 25427.08 | N12: 160000 | O12: ==(N12-H12)*G12*1.09 -> 3601 | P12: ==K12*C12+MAX(O12,0) -> 25427.08 | Q12: ==M12*12 -> 305124.96 | R12: ==C12*D12 -> 13839 | S12: ==E12*C12 -> 6590 | T12: ==F12*C12 -> 1397.08
A13: IP潮玩星球 | B13: A栋-B1-50 | C13: 50.44 | D13: 160 | E13: 50 | F13: 10.6 | G13: 0.11 | H13: ==D13*C13/G13/1.09 -> 67309.425 | I13: 80000 | J13: ==(I13-H13)*G13*1.09 -> 1521.6 | K13: ==D13+E13+F13 -> 220.6 | L13: ==(D13+E13+F13)*C13 -> 11127.064 | M13: ==K13*C13+MAX(J13,0) -> 12648.664 | N13: 80000 | O13: ==(N13-H13)*G13*1.09 -> 1521.6 | P13: ==K13*C13+MAX(O13,0) -> 12648.664 | Q13: ==M13*12 -> 151783.97 | R13: ==C13*D13 -> 8070.4 | S13: ==E13*C13 -> 2522 | T13: ==F13*C13 -> 534.664
A14: 超市 | B14: A-B1-Z01 | C14: 3836.72 | D14: 31.5 | E14: 5.25 | G14: 0.02 | I14: 4000000 | K14: ==D14+E14+F14 -> 36.75 | L14: ==(D14+E14+F14)*C14 -> 140999.46 | M14: ==K14*C14+MAX(J14,0) -> 140999.46 | N14: 4000000 | P14: ==K14*C14+MAX(O14,0) -> 140999.46 | Q14: ==M14*12 -> 1691993.5 | R14: ==C14*D14 -> 120856.68 | S14: ==E14*C14 -> 20142.78 | T14: ==F14*C14 -> 0
A15: 合计 | C15: ==SUM(C4:C14) -> 4662.75 | D15: ==R15/C15 -> 49.957617 | E15: ==S15/C15 -> 13.177691 | F15: ==T15/C15 -> 1.8778442 | J15: ==SUMIF(J4:J14,">0") -> 5431.4 | K15: ==M15/C15 -> 66.178002 | M15: ==SUM(M4:M14) -> 308571.48 | O15: ==SUMIF(O4:O14,">0") -> 7480.95 | P15: ==SUM(P4:P14) -> 310621.03 | Q15: ==SUM(Q4:Q14) -> 3702857.7 | R15: ==SUM(R3:R14) -> 232939.88 | S15: ==SUM(S3:S14) -> 61444.28 | T15: ==SUM(T3:T14) -> 8755.918
J16: ==J15/C15 -> 1.1648491 | O16: ==O15/C15 -> 1.6044073 | P16: ==P15/C15 -> 66.61756
A17: 改造后—中岛区域
A18: 品牌 | B18: 资源号 | C18: 面积 | D18: 保底租金单价 | E18: 物管单价 | F18: 推广费单价 | K18: 全含 | L18: 月总租费，不含抽成 | M18: 月总租费，含抽成 | P18: 月总租费，含抽成 | Q18: 年总租费（含税，元）
C19: （平方米） | D19: （含税，元/平方米/月） | E19: （含税，元/平方米/月） | F19: （含税，元/平方米/月） | G19: 扣点 | H19: 取高临界值 | I19: 保守预估 | J19: 保守 | N19: 激进预估 | O19: 激进抽成 | R19: 保底租金 | S19: 物业 | T19: 推广
A20: SKG | B20: A栋-B1-53 | C20: 23.44 | D20: 250 | E20: 50 | F20: 10.6 | G20: 0.11 | H20: ==D20*C20/G20/1.09 -> 48874.062 | I20: 65000 | J20: ==(I20-H20)*G20*1.09 -> 1933.5 | K20: ==D20+E20+F20 -> 310.6 | L20: ==(D20+E20+F20)*C20 -> 7280.464 | M20: ==K20*C20+MAX(J20,0) -> 9213.964 | N20: 80000 | O20: ==(N20-H20)*G20*1.09 -> 3732 | P20: ==K20*C20+MAX(O20,0) -> 11012.464 | Q20: ==M20*12 -> 110567.57 | R20: ==C20*D20 -> 5860 | S20: ==E20*C20 -> 1172 | T20: ==F20*C20 -> 248.464
A21: 添可 | B21: A栋-B1-55 | C21: 17.85 | D21: 250 | E21: 50 | F21: 10.6 | G21: 0.11 | H21: ==D21*C21/G21/1.09 -> 37218.515 | I21: 65000 | J21: ==(I21-H21)*G21*1.09 -> 3331 | K21: ==D21+E21+F21 -> 310.6 | L21: ==(D21+E21+F21)*C21 -> 5544.21 | M21: ==K21*C21+MAX(J21,0) -> 8875.21 | N21: 80000 | O21: ==(N21-H21)*G21*1.09 -> 5129.5 | P21: ==K21*C21+MAX(O21,0) -> 10673.71 | Q21: ==M21*12 -> 106502.52 | R21: ==C21*D21 -> 4462.5 | S21: ==E21*C21 -> 892.5 | T21: ==F21*C21 -> 189.21
A22: DYSON | B22: A栋-B1-56 | C22: 17.85 | D22: 250 | E22: 50 | F22: 10.6 | G22: 0.11 | H22: ==D22*C22/G22/1.09 -> 37218.515 | I22: 65000 | J22: ==(I22-H22)*G22*1.09 -> 3331 | K22: ==D22+E22+F22 -> 310.6 | L22: ==(D22+E22+F22)*C22 -> 5544.21 | M22: ==K22*C22+MAX(J22,0) -> 8875.21 | N22: 80000 | O22: ==(N22-H22)*G22*1.09 -> 5129.5 | P22: ==K22*C22+MAX(O22,0) -> 10673.71 | Q22: ==M22*12 -> 106502.52 | R22: ==C22*D22 -> 4462.5 | S22: ==E22*C22 -> 892.5 | T22: ==F22*C22 -> 189.21
A23: 李山山茶室 | B23: A栋-B1-57 | C23: 16.51 | D23: 275 | E23: 50 | F23: 10.6 | G23: 0.12 | H23: ==D23*C23/G23/1.09 -> 34711.391 | I23: 130000 | J23: ==(I23-H23)*G23*1.09 -> 12463.75 | K23: ==D23+E23+F23 -> 335.6 | L23: ==(D23+E23+F23)*C23 -> 5540.756 | M23: ==K23*C23+MAX(J23,0) -> 18004.506 | N23: 80000 | O23: ==(N23-H23)*G23*1.09 -> 5923.75 | P23: ==K23*C23+MAX(O23,0) -> 11464.506 | Q23: ==M23*12 -> 216054.07 | R23: ==C23*D23 -> 4540.25 | S23: ==E23*C23 -> 825.5 | T23: ==F23*C23 -> 175.006
A24: 李山山外摆 | B24: A栋-B1-58 | C24: 17.59 | D24: 275 | E24: 50 | F24: 10.6 | G24: 0 | H24: 0 | I24: 0 | J24: ==(I24-H24)*G24*1.09 -> 0 | K24: ==D24+E24+F24 -> 335.6 | L24: ==(D24+E24+F24)*C24 -> 5903.204 | M24: ==K24*C24+MAX(J24,0) -> 5903.204 | N24: 80000 | O24: ==(N24-H24)*G24*1.09 -> 0 | P24: ==K24*C24+MAX(O24,0) -> 5903.204 | Q24: ==M24*12 -> 70838.448 | R24: ==C24*D24 -> 4837.25 | S24: ==E24*C24 -> 879.5 | T24: ==F24*C24 -> 186.454
A25: moody美瞳 | B25: A栋-B1-59 | C25: 11.33 | D25: 335 | E25: 50 | F25: 10.6 | G25: 0.11 | H25: ==D25*C25/G25/1.09 -> 31655.963 | I25: 40000 | J25: ==(I25-H25)*G25*1.09 -> 1000.45 | K25: ==D25+E25+F25 -> 395.6 | L25: ==(D25+E25+F25)*C25 -> 4482.148 | M25: ==K25*C25+MAX(J25,0) -> 5482.598 | N25: 70000 | O25: ==(N25-H25)*G25*1.09 -> 4597.45 | P25: ==K25*C25+MAX(O25,0) -> 9079.598 | Q25: ==M25*12 -> 65791.176 | R25: ==C25*D25 -> 3795.55 | S25: ==E25*C25 -> 566.5 | T25: ==F25*C25 -> 120.098
A26: 芷甲 | B26: A栋-B1-60 | C26: 11.33 | D26: 335 | E26: 50 | F26: 10.6 | G26: 0.11 | H26: ==D26*C26/G26/1.09 -> 31655.963 | I26: 40000 | J26: ==(I26-H26)*G26*1.09 -> 1000.45 | K26: ==D26+E26+F26 -> 395.6 | L26: ==(D26+E26+F26)*C26 -> 4482.148 | M26: ==K26*C26+MAX(J26,0) -> 5482.598 | N26: 70000 | O26: ==(N26-H26)*G26*1.09 -> 4597.45 | P26: ==K26*C26+MAX(O26,0) -> 9079.598 | Q26: ==M26*12 -> 65791.176 | R26: ==C26*D26 -> 3795.55 | S26: ==E26*C26 -> 566.5 | T26: ==F26*C26 -> 120.098
A27: 结绳记 | B27: A栋-B1-61 | C27: 11.75 | D27: 335 | E27: 50 | F27: 10.6 | G27: 0.11 | H27: ==D27*C27/G27/1.09 -> 32829.441 | I27: 40000 | J27: ==(I27-H27)*G27*1.09 -> 859.75 | K27: ==D27+E27+F27 -> 395.6 | L27: ==(D27+E27+F27)*C27 -> 4648.3 | M27: ==K27*C27+MAX(J27,0) -> 5508.05 | N27: 70000 | O27: ==(N27-H27)*G27*1.09 -> 4456.75 | P27: ==K27*C27+MAX(O27,0) -> 9105.05 | Q27: ==M27*12 -> 66096.6 | R27: ==C27*D27 -> 3936.25 | S27: ==E27*C27 -> 587.5 | T27: ==F27*C27 -> 124.55
A28: 花点时间 | B28: A栋-B1-62 | C28: 10.73 | D28: 335 | E28: 50 | F28: 10.6 | G28: 0.11 | H28: ==D28*C28/G28/1.09 -> 29979.566 | I28: 50000 | J28: ==(I28-H28)*G28*1.09 -> 2400.45 | K28: ==D28+E28+F28 -> 395.6 | L28: ==(D28+E28+F28)*C28 -> 4244.788 | M28: ==K28*C28+MAX(J28,0) -> 6645.238 | N28: 70000 | O28: ==(N28-H28)*G28*1.09 -> 4798.45 | P28: ==K28*C28+MAX(O28,0) -> 9043.238 | Q28: ==M28*12 -> 79742.856 | R28: ==C28*D28 -> 3594.55 | S28: ==E28*C28 -> 536.5 | T28: ==F28*C28 -> 113.738
A29: 酥乾隆外摆 | B29: A栋-B1-63 | C29: 13.65 | D29: 275 | E29: 50 | F29: 10.6 | G29: 0 | H29: 0 | I29: 0 | J29: ==(I29-H29)*G29*1.09 -> 0 | K29: ==D29+E29+F29 -> 335.6 | L29: ==(D29+E29+F29)*C29 -> 4580.94 | M29: ==K29*C29+MAX(J29,0) -> 4580.94 | N29: 76000 | O29: ==(N29-H29)*G29*1.09 -> 0 | P29: ==K29*C29+MAX(O29,0) -> 4580.94 | Q29: ==M29*12 -> 54971.28 | R29: ==C29*D29 -> 3753.75 | S29: ==E29*C29 -> 682.5 | T29: ==F29*C29 -> 144.69
A30: 丹香外摆 | B30: A栋-B1-65 | C30: 13.65 | D30: 275 | E30: 50 | F30: 10.6 | G30: 0 | H30: 0 | I30: 0 | J30: ==(I30-H30)*G30*1.09 -> 0 | K30: ==D30+E30+F30 -> 335.6 | L30: ==(D30+E30+F30)*C30 -> 4580.94 | M30: ==K30*C30+MAX(J30,0) -> 4580.94 | N30: 76000 | O30: ==(N30-H30)*G30*1.09 -> 0 | P30: ==K30*C30+MAX(O30,0) -> 4580.94 | Q30: ==M30*12 -> 54971.28 | R30: ==C30*D30 -> 3753.75 | S30: ==E30*C30 -> 682.5 | T30: ==F30*C30 -> 144.69
A31: 名之屋 | B31: A栋-B1-66 | C31: 16.52 | D31: 335 | E31: 50 | F31: 10.6 | G31: 0.12 | H31: ==D31*C31/G31/1.09 -> 42310.398 | I31: 76000 | J31: ==(I31-H31)*G31*1.09 -> 4406.6 | K31: ==D31+E31+F31 -> 395.6 | L31: ==(D31+E31+F31)*C31 -> 6535.312 | M31: ==K31*C31+MAX(J31,0) -> 10941.912 | N31: 90000 | O31: ==(N31-H31)*G31*1.09 -> 6237.8 | P31: ==K31*C31+MAX(O31,0) -> 12773.112 | Q31: ==M31*12 -> 131302.94 | R31: ==C31*D31 -> 5534.2 | S31: ==E31*C31 -> 826 | T31: ==F31*C31 -> 175.112
A32: 鸡蛋仔 | B32: A栋-B1-67 | C32: 14.47 | D32: 335 | E32: 50 | F32: 10.6 | G32: 0.12 | H32: ==D32*C32/G32/1.09 -> 37060.015 | I32: 76000 | J32: ==(I32-H32)*G32*1.09 -> 5093.35 | K32: ==D32+E32+F32 -> 395.6 | L32: ==(D32+E32+F32)*C32 -> 5724.332 | M32: ==K32*C32+MAX(J32,0) -> 10817.682 | N32: 76000 | O32: ==(N32-H32)*G32*1.09 -> 5093.35 | P32: ==K32*C32+MAX(O32,0) -> 10817.682 | Q32: ==M32*12 -> 129812.18 | R32: ==C32*D32 -> 4847.45 | S32: ==E32*C32 -> 723.5 | T32: ==F32*C32 -> 153.382
A33: 有堂古 | B33: A栋-B1-68 | C33: 16.24 | D33: 335 | E33: 50 | F33: 10.6 | G33: 0.12 | H33: ==D33*C33/G33/1.09 -> 41593.272 | I33: 76000 | J33: ==(I33-H33)*G33*1.09 -> 4500.4 | K33: ==D33+E33+F33 -> 395.6 | L33: ==(D33+E33+F33)*C33 -> 6424.544 | M33: ==K33*C33+MAX(J33,0) -> 10924.944 | N33: 80000 | O33: ==(N33-H33)*G33*1.09 -> 5023.6 | P33: ==K33*C33+MAX(O33,0) -> 11448.144 | Q33: ==M33*12 -> 131099.33 | R33: ==C33*D33 -> 5440.4 | S33: ==E33*C33 -> 812 | T33: ==F33*C33 -> 172.144
A34: 鲜目录寿司 | B34: A栋-B1-69 | C34: 14.8 | D34: 335 | E34: 50 | F34: 10.6 | G34: 0.12 | H34: ==D34*C34/G34/1.09 -> 37905.199 | I34: 76000 | J34: ==(I34-H34)*G34*1.09 -> 4982.8 | K34: ==D34+E34+F34 -> 395.6 | L34: ==(D34+E34+F34)*C34 -> 5854.88 | M34: ==K34*C34+MAX(J34,0) -> 10837.68 | N34: 80000 | O34: ==(N34-H34)*G34*1.09 -> 5506 | P34: ==K34*C34+MAX(O34,0) -> 11360.88 | Q34: ==M34*12 -> 130052.16 | R34: ==C34*D34 -> 4958 | S34: ==E34*C34 -> 740 | T34: ==F34*C34 -> 156.88
A35: 藤田关东煮 | B35: A栋-B1-70 | C35: 12.4 | D35: 335 | E35: 50 | F35: 10.6 | G35: 0.12 | H35: ==D35*C35/G35/1.09 -> 31758.41 | I35: 76000 | J35: ==(I35-H35)*G35*1.09 -> 5786.8 | K35: ==D35+E35+F35 -> 395.6 | L35: ==(D35+E35+F35)*C35 -> 4905.44 | M35: ==K35*C35+MAX(J35,0) -> 10692.24 | N35: 75000 | O35: ==(N35-H35)*G35*1.09 -> 5656 | P35: ==K35*C35+MAX(O35,0) -> 10561.44 | Q35: ==M35*12 -> 128306.88 | R35: ==C35*D35 -> 4154 | S35: ==E35*C35 -> 620 | T35: ==F35*C35 -> 131.44
A36: 李磊与韩梅梅 | B36: A栋-B1-71 | C36: 15.2 | D36: 335 | E36: 50 | F36: 10.6 | G36: 0.12 | H36: ==D36*C36/G36/1.09 -> 38929.664 | I36: 76000 | J36: ==(I36-H36)*G36*1.09 -> 4848.8 | K36: ==D36+E36+F36 -> 395.6 | L36: ==(D36+E36+F36)*C36 -> 6013.12 | M36: ==K36*C36+MAX(J36,0) -> 10861.92 | N36: 80000 | O36: ==(N36-H36)*G36*1.09 -> 5372 | P36: ==K36*C36+MAX(O36,0) -> 11385.12 | Q36: ==M36*12 -> 130343.04 | R36: ==C36*D36 -> 5092 | S36: ==E36*C36 -> 760 | T36: ==F36*C36 -> 161.12
A37: 蒂娜朵拉 | B37: A栋-B1-72 | C37: 12.91 | D37: 335 | E37: 50 | F37: 10.6 | G37: 0.12 | H37: ==D37*C37/G37/1.09 -> 33064.602 | I37: 76000 | J37: ==(I37-H37)*G37*1.09 -> 5615.95 | K37: ==D37+E37+F37 -> 395.6 | L37: ==(D37+E37+F37)*C37 -> 5107.196 | M37: ==K37*C37+MAX(J37,0) -> 10723.146 | N37: 76000 | O37: ==(N37-H37)*G37*1.09 -> 5615.95 | P37: ==K37*C37+MAX(O37,0) -> 10723.146 | Q37: ==M37*12 -> 128677.75 | R37: ==C37*D37 -> 4324.85 | S37: ==E37*C37 -> 645.5 | T37: ==F37*C37 -> 136.846
A38: 糖叙外摆 | B38: A栋-B1-73 | C38: 15.38 | D38: 275 | E38: 50 | F38: 10.6 | G38: 0 | H38: 0 | I38: 0 | J38: ==(I38-H38)*G38*1.09 -> 0 | K38: ==D38+E38+F38 -> 335.6 | L38: ==(D38+E38+F38)*C38 -> 5161.528 | M38: ==K38*C38+MAX(J38,0) -> 5161.528 | N38: 78000 | O38: ==(N38-H38)*G38*1.09 -> 0 | P38: ==K38*C38+MAX(O38,0) -> 5161.528 | Q38: ==M38*12 -> 61938.336 | R38: ==C38*D38 -> 4229.5 | S38: ==E38*C38 -> 769 | T38: ==F38*C38 -> 163.028
A39: 巧克叔叔 | B39: A栋-B1-75 | C39: 17.51 | D39: 335 | E39: 50 | F39: 10.6 | G39: 0.12 | H39: ==D39*C39/G39/1.09 -> 44845.948 | I39: 80000 | J39: ==(I39-H39)*G39*1.09 -> 4598.15 | K39: ==D39+E39+F39 -> 395.6 | L39: ==(D39+E39+F39)*C39 -> 6926.956 | M39: ==K39*C39+MAX(J39,0) -> 11525.106 | N39: 80000 | O39: ==(N39-H39)*G39*1.09 -> 4598.15 | P39: ==K39*C39+MAX(O39,0) -> 11525.106 | Q39: ==M39*12 -> 138301.27 | R39: ==C39*D39 -> 5865.85 | S39: ==E39*C39 -> 875.5 | T39: ==F39*C39 -> 185.606
A40: 糖小妙 | B40: A栋-B1-76 | C40: 17.83 | D40: 335 | E40: 50 | F40: 10.6 | G40: 0.12 | H40: ==D40*C40/G40/1.09 -> 45665.52 | I40: 80000 | J40: ==(I40-H40)*G40*1.09 -> 4490.95 | K40: ==D40+E40+F40 -> 395.6 | L40: ==(D40+E40+F40)*C40 -> 7053.548 | M40: ==K40*C40+MAX(J40,0) -> 11544.498 | N40: 80000 | O40: ==(N40-H40)*G40*1.09 -> 4490.95 | P40: ==K40*C40+MAX(O40,0) -> 11544.498 | Q40: ==M40*12 -> 138533.98 | R40: ==C40*D40 -> 5973.05 | S40: ==E40*C40 -> 891.5 | T40: ==F40*C40 -> 188.998
A41: fufuland | B41: A栋-B1-77 | C41: 17.83 | D41: 335 | E41: 50 | F41: 10.6 | G41: 0.12 | H41: ==D41*C41/G41/1.09 -> 45665.52 | I41: 80000 | J41: ==(I41-H41)*G41*1.09 -> 4490.95 | K41: ==D41+E41+F41 -> 395.6 | L41: ==(D41+E41+F41)*C41 -> 7053.548 | M41: ==K41*C41+MAX(J41,0) -> 11544.498 | N41: 80000 | O41: ==(N41-H41)*G41*1.09 -> 4490.95 | P41: ==K41*C41+MAX(O41,0) -> 11544.498 | Q41: ==M41*12 -> 138533.98 | R41: ==C41*D41 -> 5973.05 | S41: ==E41*C41 -> 891.5 | T41: ==F41*C41 -> 188.998
A42: 泰柯茶园 | B42: A栋-B1-78 | C42: 40.53 | D42: 195 | E42: 50 | F42: 10.6 | G42: 0.12 | H42: ==D42*C42/G42/1.09 -> 60423.165 | I42: 120000 | J42: ==(I42-H42)*G42*1.09 -> 7792.65 | K42: ==D42+E42+F42 -> 255.6 | L42: ==(D42+E42+F42)*C42 -> 10359.468 | M42: ==K42*C42+MAX(J42,0) -> 18152.118 | N42: 150000 | O42: ==(N42-H42)*G42*1.09 -> 11716.65 | P42: ==K42*C42+MAX(O42,0) -> 22076.118 | Q42: ==M42*12 -> 217825.42 | R42: ==C42*D42 -> 7903.35 | S42: ==E42*C42 -> 2026.5 | T42: ==F42*C42 -> 429.618
A43: 合计 | C43: ==SUM(C20:C42) -> 377.3 | D43: ==R43/C43 -> 294.42778 | E43: ==S43/C43 -> 50 | F43: ==T43/C43 -> 10.6 | J43: ==SUMIF(J20:J42,">0") -> 82927.75 | K43: ==M43/C43 -> 574.82038 | M43: ==SUM(M20:M42) -> 216879.73 | O43: ==SUMIF(O20:O42,">0") -> 102166.25 | P43: ==SUM(P20:P42) -> 236118.23 | Q43: ==SUM(Q20:Q42) -> 2602556.8 | R43: ==SUM(R20:R42) -> 111087.6 | S43: ==SUM(S20:S42) -> 18865 | T43: ==SUM(T20:T42) -> 3999.38
A45: 改造后-边铺合计
A46: 品牌 | B46: 资源号 | C46: 面积 | D46: 保底租金单价 | E46: 物管单价 | F46: 推广费单价 | K46: 全含 | L46: 月总租费，不含抽成 | M46: 月总租费，含抽成 | Q46: 年总租费（含税，元）
C47: （平方米） | D47: （含税，元/平方米/月） | E47: （含税，元/平方米/月） | F47: （含税，元/平方米/月） | G47: 扣点 | H47: 取高临界值 | I47: 销售额预估 | J47: 预估抽成收入 | R47: 保底租金 | S47: 物业 | T47: 推广 | U47: 合同收铺日期
A48: 比木.卡西西 | B48: A栋-B1-01 | C48: 142.42 | D48: 55 | E48: 20 | F48: 10.6 | G48: 0.08 | H48: ==D48*C48/G48/1.09 -> 89829.128 | I48: 50000 | J48: ==(I48-H48)*G48*1.09 -> -3473.1 | K48: ==D48+E48+F48 -> 85.6 | L48: ==(D48+E48+F48)*C48 -> 12191.152 | M48: ==K48*C48+MAX(J48,0) -> 12191.152 | Q48: ==M48*12 -> 146293.82 | R48: ==C48*D48 -> 7833.1 | S48: ==E48*C48 -> 2848.4 | T48: ==F48*C48 -> 1509.652 | U48: 46387
A49: 嗨嗨儿 | B49: A栋-B1-02 | C49: 119.87 | D49: 55 | E49: 20 | F49: 5 | G49: 0.09 | H49: ==D49*C49/G49/1.09 -> 67205.403 | I49: 80000 | J49: ==(I49-H49)*G49*1.09 -> 1255.15 | K49: ==D49+E49+F49 -> 80 | L49: ==(D49+E49+F49)*C49 -> 9589.6 | M49: ==K49*C49+MAX(J49,0) -> 10844.75 | Q49: ==M49*12 -> 130137 | R49: ==C49*D49 -> 6592.85 | S49: ==E49*C49 -> 2397.4 | T49: ==F49*C49 -> 599.35 | U49: 46586
A50: 犟骨头超级排骨饭 | B50: A栋-B1-03 | C50: 62.56 | D50: 200 | E50: 50 | F50: 10.6 | G50: 0.125 | H50: ==D50*C50/G50/1.09 -> 91831.193 | I50: 120000 | J50: ==(I50-H50)*G50*1.09 -> 3838 | K50: ==D50+E50+F50 -> 260.6 | L50: ==(D50+E50+F50)*C50 -> 16303.136 | M50: ==K50*C50+MAX(J50,0) -> 20141.136 | Q50: ==M50*12 -> 241693.63 | R50: ==C50*D50 -> 12512 | S50: ==E50*C50 -> 3128 | T50: ==F50*C50 -> 663.136 | U50: 46151
A51: 品秦川 | B51: A栋-B1-05 | C51: 148.01 | D51: 130 | E51: 50 | F51: 10.6 | G51: 0.12 | H51: ==D51*C51/G51/1.09 -> 147104.74 | I51: 120000 | J51: ==(I51-H51)*G51*1.09 -> -3545.3 | K51: ==D51+E51+F51 -> 190.6 | L51: ==(D51+E51+F51)*C51 -> 28210.706 | M51: ==K51*C51+MAX(J51,0) -> 28210.706 | Q51: ==M51*12 -> 338528.47 | R51: ==C51*D51 -> 19241.3 | S51: ==E51*C51 -> 7400.5 | T51: ==F51*C51 -> 1568.906 | U51: 46341
A52: 空铺-尹三顺 | B52: A栋-B1-06 | C52: 65.3 | D52: 65 | E52: 30 | F52: 10.6 | G52: 0.06 | H52: ==D52*C52/G52/1.09 -> 64900.612 | I52: 100000 | J52: ==(I52-H52)*G52*1.09 -> 2295.5 | K52: ==D52+E52+F52 -> 105.6 | L52: ==(D52+E52+F52)*C52 -> 6895.68 | M52: ==K52*C52+MAX(J52,0) -> 9191.18 | Q52: ==M52*12 -> 110294.16 | R52: ==C52*D52 -> 4244.5 | S52: ==E52*C52 -> 1959 | T52: ==F52*C52 -> 692.18
A53: 空铺-尹三顺 | B53: A栋-B1-07 | C53: 140.27 | D53: 65 | E53: 30 | F53: 10.6 | G53: 0.06 | H53: ==D53*C53/G53/1.09 -> 139412.08 | I53: 200000 | J53: ==(I53-H53)*G53*1.09 -> 3962.45 | K53: ==D53+E53+F53 -> 105.6 | L53: ==(D53+E53+F53)*C53 -> 14812.512 | M53: ==K53*C53+MAX(J53,0) -> 18774.962 | Q53: ==M53*12 -> 225299.54 | R53: ==C53*D53 -> 9117.55 | S53: ==E53*C53 -> 4208.1 | T53: ==F53*C53 -> 1486.862
A54: 空铺-尹三顺 | B54: A栋-B1-08 | C54: 99.41 | D54: 65 | E54: 30 | F54: 10.6 | G54: 0.06 | H54: ==D54*C54/G54/1.09 -> 98801.988 | I54: 100000 | J54: ==(I54-H54)*G54*1.09 -> 78.35 | K54: ==D54+E54+F54 -> 105.6 | L54: ==(D54+E54+F54)*C54 -> 10497.696 | M54: ==K54*C54+MAX(J54,0) -> 10576.046 | Q54: ==M54*12 -> 126912.55 | R54: ==C54*D54 -> 6461.65 | S54: ==E54*C54 -> 2982.3 | T54: ==F54*C54 -> 1053.746
A55: 空铺-丹香 | B55: A栋-B1-09 | C55: 70.39 | D55: 150 | E55: 50 | F55: 10.6 | G55: 0.1 | H55: ==D55*C55/G55/1.09 -> 96866.972 | I55: 150000 | J55: ==(I55-H55)*G55*1.09 -> 5791.5 | K55: ==D55+E55+F55 -> 210.6 | L55: ==(D55+E55+F55)*C55 -> 14824.134 | M55: ==K55*C55+MAX(J55,0) -> 20615.634 | Q55: ==M55*12 -> 247387.61 | R55: ==C55*D55 -> 10558.5 | S55: ==E55*C55 -> 3519.5 | T55: ==F55*C55 -> 746.134
A56: 花小福 | B56: A栋-B1-10 | C56: 74.22 | D56: 123.05 | E56: 50 | F56: 5 | G56: 0.06 | H56: ==D56*C56/G56/1.09 -> 139644.82 | I56: 150000 | J56: ==(I56-H56)*G56*1.09 -> 677.229 | K56: ==D56+E56+F56 -> 178.05 | L56: ==(D56+E56+F56)*C56 -> 13214.871 | M56: ==K56*C56+MAX(J56,0) -> 13892.1 | Q56: ==M56*12 -> 166705.2 | R56: ==C56*D56 -> 9132.771 | S56: ==E56*C56 -> 3711 | T56: ==F56*C56 -> 371.1 | U56: 46385
A57: 花小福 | B57: A栋-B1-11a | C57: 80.63 | D57: 123.05 | E57: 50 | F57: 5 | G57: 0.06 | H57: ==D57*C57/G57/1.09 -> 151705.22 | I57: 150000 | J57: ==(I57-H57)*G57*1.09 -> -111.5215 | K57: ==D57+E57+F57 -> 178.05 | L57: ==(D57+E57+F57)*C57 -> 14356.172 | M57: ==K57*C57+MAX(J57,0) -> 14356.172 | Q57: ==M57*12 -> 172274.06 | R57: ==C57*D57 -> 9921.5215 | S57: ==E57*C57 -> 4031.5 | T57: ==F57*C57 -> 403.15 | U57: 46385
A58: 暖溢-酥乾隆 | B58: A栋-B1-11b | C58: 95.24 | D58: 90 | E58: 50 | F58: 10.6 | G58: 0.08 | H58: ==D58*C58/G58/1.09 -> 98298.165 | I58: 150000 | J58: ==(I58-H58)*G58*1.09 -> 4508.4 | K58: ==D58+E58+F58 -> 150.6 | L58: ==(D58+E58+F58)*C58 -> 14343.144 | M58: ==K58*C58+MAX(J58,0) -> 18851.544 | Q58: ==M58*12 -> 226218.53 | R58: ==C58*D58 -> 8571.6 | S58: ==E58*C58 -> 4762 | T58: ==F58*C58 -> 1009.544 | U58: 46148
A59: 空铺-奈雪 | B59: A栋-B1-12a | C59: 34.86 | D59: 150 | E59: 50 | F59: 10.6 | G59: 0.11 | H59: ==D59*C59/G59/1.09 -> 43611.343 | I59: 75000 | J59: ==(I59-H59)*G59*1.09 -> 3763.5 | K59: ==D59+E59+F59 -> 210.6 | L59: ==(D59+E59+F59)*C59 -> 7341.516 | M59: ==K59*C59+MAX(J59,0) -> 11105.016 | Q59: ==M59*12 -> 133260.19 | R59: ==C59*D59 -> 5229 | S59: ==E59*C59 -> 1743 | T59: ==F59*C59 -> 369.516
A60: 空铺-奈雪 | B60: A栋-B1-12b | C60: 31.59 | D60: 150 | E60: 50 | F60: 10.6 | G60: 0.11 | H60: ==D60*C60/G60/1.09 -> 39520.434 | I60: 75000 | J60: ==(I60-H60)*G60*1.09 -> 4254 | K60: ==D60+E60+F60 -> 210.6 | L60: ==(D60+E60+F60)*C60 -> 6652.854 | M60: ==K60*C60+MAX(J60,0) -> 10906.854 | Q60: ==M60*12 -> 130882.25 | R60: ==C60*D60 -> 4738.5 | S60: ==E60*C60 -> 1579.5 | T60: ==F60*C60 -> 334.854
A61: 同方药业-杯子星球 | B61: A栋-B1-13 | C61: 84.65 | D61: 150 | E61: 50 | F61: 10.6 | G61: 0.08 | H61: ==D61*C61/G61/1.09 -> 145613.53 | I61: 100000 | J61: ==(I61-H61)*G61*1.09 -> -3977.5 | K61: ==D61+E61+F61 -> 210.6 | L61: ==(D61+E61+F61)*C61 -> 17827.29 | M61: ==K61*C61+MAX(J61,0) -> 17827.29 | Q61: ==M61*12 -> 213927.48 | R61: ==C61*D61 -> 12697.5 | S61: ==E61*C61 -> 4232.5 | T61: ==F61*C61 -> 897.29 | U61: 46142
A62: 转转 | B62: A栋-B1-15 | C62: 84.47 | D62: 138.8 | E62: 50 | F62: 10.6 | G62: 0.04 | H62: ==D62*C62/G62/1.09 -> 268909.08 | I62: 60000 | J62: ==(I62-H62)*G62*1.09 -> -9108.436 | K62: ==D62+E62+F62 -> 199.4 | L62: ==(D62+E62+F62)*C62 -> 16843.318 | M62: ==K62*C62+MAX(J62,0) -> 16843.318 | Q62: ==M62*12 -> 202119.82 | R62: ==C62*D62 -> 11724.436 | S62: ==E62*C62 -> 4223.5 | T62: ==F62*C62 -> 895.382 | U62: 46265
A63: 洗脸猫-N 1 | B63: A栋-B1-16 | C63: 62.25 | D63: 160 | E63: 50 | F63: 10.6 | G63: 0.12 | H63: ==D63*C63/G63/1.09 -> 76146.789 | I63: 80000 | J63: ==(I63-H63)*G63*1.09 -> 504 | K63: ==D63+E63+F63 -> 220.6 | L63: ==(D63+E63+F63)*C63 -> 13732.35 | M63: ==K63*C63+MAX(J63,0) -> 14236.35 | Q63: ==M63*12 -> 170836.2 | R63: ==C63*D63 -> 9960 | S63: ==E63*C63 -> 3112.5 | T63: ==F63*C63 -> 659.85 | U63: 46159
A64: 酥乾隆-瑞幸 | B64: A栋-B1-17 | C64: 95.3 | D64: 100 | E64: 50 | F64: 10.6 | G64: 0.1 | H64: ==D64*C64/G64/1.09 -> 87431.193 | I64: 150000 | J64: ==(I64-H64)*G64*1.09 -> 6820 | K64: ==D64+E64+F64 -> 160.6 | L64: ==(D64+E64+F64)*C64 -> 15305.18 | M64: ==K64*C64+MAX(J64,0) -> 22125.18 | Q64: ==M64*12 -> 265502.16 | R64: ==C64*D64 -> 9530 | S64: ==E64*C64 -> 4765 | T64: ==F64*C64 -> 1010.18 | U64: 46168
A65: 阿水大杯茶-PC+满巍明 | B65: A栋-B1-18 | C65: 25.36 | D65: 500 | E65: 50 | F65: 10.6 | G65: 0.12 | H65: ==D65*C65/G65/1.09 -> 96941.896 | I65: 120000 | J65: ==(I65-H65)*G65*1.09 -> 3016 | K65: ==D65+E65+F65 -> 560.6 | L65: ==(D65+E65+F65)*C65 -> 14216.816 | M65: ==K65*C65+MAX(J65,0) -> 17232.816 | Q65: ==M65*12 -> 206793.79 | R65: ==C65*D65 -> 12680 | S65: ==E65*C65 -> 1268 | T65: ==F65*C65 -> 268.816 | U65: 46203
A66: 喜样 | B66: A栋-B1-19 | C66: 85.87 | D66: 140 | E66: 50 | F66: 10.6 | G66: 0.11 | H66: ==D66*C66/G66/1.09 -> 100265.22 | I66: 120000 | J66: ==(I66-H66)*G66*1.09 -> 2366.2 | K66: ==D66+E66+F66 -> 200.6 | L66: ==(D66+E66+F66)*C66 -> 17225.522 | M66: ==K66*C66+MAX(J66,0) -> 19591.722 | Q66: ==M66*12 -> 235100.66 | R66: ==C66*D66 -> 12021.8 | S66: ==E66*C66 -> 4293.5 | T66: ==F66*C66 -> 910.222 | U66: 46275
A67: 蒙自源 | B67: A栋-B1-20 | C67: 96.44 | D67: 140 | E67: 50 | F67: 10.6 | G67: 0.11 | H67: ==D67*C67/G67/1.09 -> 112607.17 | I67: 120000 | J67: ==(I67-H67)*G67*1.09 -> 886.4 | K67: ==D67+E67+F67 -> 200.6 | L67: ==(D67+E67+F67)*C67 -> 19345.864 | M67: ==K67*C67+MAX(J67,0) -> 20232.264 | Q67: ==M67*12 -> 242787.17 | R67: ==C67*D67 -> 13501.6 | S67: ==E67*C67 -> 4822 | T67: ==F67*C67 -> 1022.264 | U67: 46335
A68: 空铺 | B68: A栋-B1-21 | C68: 107.66 | D68: 135 | E68: 50 | F68: 10.6 | G68: 0.11 | H68: ==D68*C68/G68/1.09 -> 121218.52 | I68: 120000 | J68: ==(I68-H68)*G68*1.09 -> -146.1 | K68: ==D68+E68+F68 -> 195.6 | L68: ==(D68+E68+F68)*C68 -> 21058.296 | M68: ==K68*C68+MAX(J68,0) -> 21058.296 | Q68: ==M68*12 -> 252699.55 | R68: ==C68*D68 -> 14534.1 | S68: ==E68*C68 -> 5383 | T68: ==F68*C68 -> 1141.196
A69: 喻记南派 | B69: A栋-B1-22 | C69: 86.48 | D69: 162 | E69: 60 | F69: 10.6 | G69: 0.14 | H69: ==D69*C69/G69/1.09 -> 91807.077 | I69: 80000 | J69: ==(I69-H69)*G69*1.09 -> -1801.76 | K69: ==D69+E69+F69 -> 232.6 | L69: ==(D69+E69+F69)*C69 -> 20115.248 | M69: ==K69*C69+MAX(J69,0) -> 20115.248 | Q69: ==M69*12 -> 241382.98 | R69: ==C69*D69 -> 14009.76 | S69: ==E69*C69 -> 5188.8 | T69: ==F69*C69 -> 916.688 | U69: 46139
A70: 岛姜家 | B70: A栋-B1-23 | C70: 113.02 | D70: 80 | E70: 50 | F70: 10.6 | G70: 0.06 | H70: ==D70*C70/G70/1.09 -> 138250.76 | I70: 150000 | J70: ==(I70-H70)*G70*1.09 -> 768.4 | K70: ==D70+E70+F70 -> 140.6 | L70: ==(D70+E70+F70)*C70 -> 15890.612 | M70: ==K70*C70+MAX(J70,0) -> 16659.012 | Q70: ==M70*12 -> 199908.14 | R70: ==C70*D70 -> 9041.6 | S70: ==E70*C70 -> 5651 | T70: ==F70*C70 -> 1198.012 | U70: 46132
A71: 嗨特购 | B71: A栋-B1-25 | C71: 154.88 | D71: 80 | E71: 50 | F71: 10.6 | G71: 0.06 | H71: ==D71*C71/G71/1.09 -> 189455.66 | I71: 150000 | J71: ==(I71-H71)*G71*1.09 -> -2580.4 | K71: ==D71+E71+F71 -> 140.6 | L71: ==(D71+E71+F71)*C71 -> 21776.128 | M71: ==K71*C71+MAX(J71,0) -> 21776.128 | Q71: ==M71*12 -> 261313.54 | R71: ==C71*D71 -> 12390.4 | S71: ==E71*C71 -> 7744 | T71: ==F71*C71 -> 1641.728 | U71: 46505
A72: 嗨特购 | B72: A栋-B1-26 | C72: 47.51 | D72: 80 | E72: 50 | F72: 10.6 | G72: 0.06 | H72: ==D72*C72/G72/1.09 -> 58116.208 | I72: 150000 | J72: ==(I72-H72)*G72*1.09 -> 6009.2 | K72: ==D72+E72+F72 -> 140.6 | L72: ==(D72+E72+F72)*C72 -> 6679.906 | M72: ==K72*C72+MAX(J72,0) -> 12689.106 | Q72: ==M72*12 -> 152269.27 | R72: ==C72*D72 -> 3800.8 | S72: ==E72*C72 -> 2375.5 | T72: ==F72*C72 -> 503.606 | U72: 46505
A73: 合计 | C73: ==SUM(C48:C72) -> 2208.66 | D73: ==R73/C73 -> 113.21201 | E73: ==S73/C73 -> 44.067217 | F73: ==T73/C73 -> 9.9034546 | J73: ==SUMIF(J48:J72,">0") -> 50794.279 | K73: ==M73/C73 -> 190.18046 | M73: ==SUM(M48:M72) -> 420043.98 | Q73: ==SUM(Q48:Q72) -> 5040527.8 | R73: ==SUM(R48:R72) -> 250046.84 | S73: ==SUM(S48:S72) -> 97329.5 | T73: ==SUM(T48:T72) -> 21873.364
A76: 区域 | B76: 面积 | C76: 现行保底租金单价 | D76: 物管单价 | E76: 推广费单价 | F76: 抽成保守 | G76: 抽成激进 | H76: 固定租金 | I76: 全含保守 | J76: 全含激进 | K76: 月总租费，含抽成
B77: （平方米） | C77: （含税，元/平方米/月） | D77: （含税，元/平方米/月） | E77: （含税，元/平方米/月） | F77: （含税，元/平方米/月） | L77: 保底租金 | M77: 物业 | N77: 推广 | O77: 抽成保守 | P77: 抽成激进
A78: 改造后—超市区域合计 | B78: ==C15 -> 4662.75 | C78: ==D15 -> 49.957617 | D78: ==E15 -> 13.177691 | E78: ==F15 -> 1.8778442 | F78: ==J15/C15 -> 1.1648491 | G78: ==O15/C15 -> 1.6044073 | H78: ==(L78+M78+N78)/B78 -> 65.013153 | I78: ==(L78+M78+N78+O78)/B78 -> 66.178002 | J78: ==(L78+M78+N78+O78+P78)/B78 -> 67.782409 | K78: ==M15 -> 308571.48 | L78: ==C78*B78 -> 232939.88 | M78: ==D78*B78 -> 61444.28 | N78: ==E78*B78 -> 8755.918 | O78: ==F78*B78 -> 5431.4 | P78: ==G78*B78 -> 7480.95
A79: 改造后—中岛合计 | B79: ==C43 -> 377.3 | C79: ==D43 -> 294.42778 | D79: ==E43 -> 50 | E79: ==F43 -> 10.6 | F79: ==J43/C43 -> 219.79261 | G79: ==O43/C43 -> 270.78253 | H79: ==(L79+M79+N79)/B79 -> 355.02778 | I79: ==(L79+M79+N79+O79)/B79 -> 574.82038 | J79: ==(L79+M79+N79+O79+P79)/B79 -> 845.60292 | K79: ==M43 -> 216879.73 | L79: ==C79*B79 -> 111087.6 | M79: ==D79*B79 -> 18865 | N79: ==E79*B79 -> 3999.38 | O79: ==F79*B79 -> 82927.75 | P79: ==G79*B79 -> 102166.25
A80: 改造后-边铺合计 | B80: ==C73 -> 2208.66 | C80: ==D73 -> 113.21201 | D80: ==E73 -> 44.067217 | E80: ==F73 -> 9.9034546 | F80: ==J73/C73 -> 22.997781 | G80: ==J73/C73 -> 22.997781 | H80: ==(L80+M80+N80)/B80 -> 167.18268 | I80: ==(L80+M80+N80+O80)/B80 -> 190.18046 | J80: ==(L80+M80+N80+O80+P80)/B80 -> 213.17824 | K80: ==M73 -> 420043.98 | L80: ==C80*B80 -> 250046.84 | M80: ==D80*B80 -> 97329.5 | N80: ==E80*B80 -> 21873.364 | O80: ==F80*B80 -> 50794.279 | P80: ==G80*B80 -> 50794.279
A81: 汇总 | B81: ==SUM(B78:B80) -> 7248.71 | C81: ==L81/B81 -> 81.955868 | D81: ==M81/B81 -> 24.506261 | E81: ==N81/B81 -> 4.7772172 | F81: ==O81/B81 -> 19.196992 | G81: ==P81/B81 -> 22.133797 | H81: ==(L81+M81+N81)/B81 -> 111.23935 | I81: ==(L81+M81+N81+O81)/B81 -> 130.43634 | J81: ==(L81+M81+N81+O81+P81)/B81 -> 152.57014 | K81: ==SUM(K78:K80) -> 945495.19 | L81: ==SUM(L78:L80) -> 594074.32 | M81: ==SUM(M78:M80) -> 177638.78 | N81: ==SUM(N78:N80) -> 34628.662 | O81: ==SUM(O78:O80) -> 139153.43 | P81: ==SUM(P78:P80) -> 160441.48
A82: 不含超市 | B82: ==B81-C14 -> 3411.99 | C82: ==L82/B82 -> 138.69256 | D82: ==M82/B82 -> 46.159573 | E82: ==N82/B82 -> 10.14911 | F82: ==O82/B82 -> 40.783657 | G82: ==P82/B82 -> 47.022846 | I82: ==SUM(C82:F82) -> 235.7849 | J82: ==SUM(C82:F82) -> 235.7849 | L82: ==L81-R14 -> 473217.64 | M82: ==M81-S14 -> 157496 | N82: ==N81-T14 -> 34628.662 | O82: ==O81 -> 139153.43 | P82: ==P81 -> 160441.48
I85: 固租单价（不含抽成） | J85: 保守抽成 | K85: 激进抽成 | L85: 全含
C86: 租费 | D86: 面积 | E86: 单价 | H86: 10.6 | I86: ==H81 -> 111.23935 | J86: ==I81 -> 130.43634 | K86: ==J81 -> 152.57014
B87: B1（含超市含空铺） | C87: 683927.6 | D87: 9239.2 | E87: 74.024547 | H87: 5 | I87: ==[1]B1投资测算!P71 -> #REF! | J87: ==[1]B1投资测算!Q71 -> #REF! | K87: ==[1]B1投资测算!T71 -> #REF!
B88: B1（不含超市） | C88: 436237.74 | D88: 2499.34 | E88: 174.54118 | H88: 差异 | I88: ==I87-I86 -> #REF! | J88: ==J87-J86 -> #REF! | K88: ==K87-K86 -> #REF!
B89: B1（不含超市不含空铺） | C89: 390109.64 | D89: 1997.77 | E89: 195.27255 | H89: 递增比例 | I89: ==I87/I86-1 -> #REF! | J89: ==J87/J86-1 -> #REF! | K89: ==K87/K86-1 -> #REF!
B90: B1（含超市） | C90: 637799.5 | D90: 8737.63 | E90: 72.994565
